cirdhighspeedcoverter/README.MD
cirdhighspeedcoverter/__init__.py
cirdhighspeedcoverter/requirements.txt
cirdhighspeedcoverter/thirdparty.json
cirdhighspeedcoverter-0.10.dist-info/LICENSE.rst
cirdhighspeedcoverter-0.10.dist-info/METADATA
cirdhighspeedcoverter-0.10.dist-info/WHEEL
cirdhighspeedcoverter-0.10.dist-info/top_level.txt
cirdhighspeedcoverter-0.10.dist-info/RECORD
