Metadata-Version: 2.1
Name: cirdhighspeedcoverter
Version: 0.10
Summary: High speed conversion of IP addresses represented in CIDR notation into their corresponding start and end IPs, along with their respective subnet masks.
Home-page: https://github.com/hansalemaos/cirdhighspeedcoverter
Author: Johannes Fischer
Author-email: aulasparticularesdealemaosp@gmail.com
License: MIT
Keywords: CIDR,convert
Classifier: Development Status :: 4 - Beta
Classifier: Programming Language :: Python :: 3 :: Only
Classifier: Programming Language :: Python :: 3.10
Classifier: Topic :: Software Development :: Libraries :: Python Modules
Classifier: Topic :: Utilities
License-File: LICENSE.rst
Requires-Dist: numexpr
Requires-Dist: numpy
Requires-Dist: pandas
